MedPy2-0.0.2.data/scripts/medpy_anisotropic_diffusion.py
MedPy2-0.0.2.data/scripts/medpy_apparent_diffusion_coefficient.py
MedPy2-0.0.2.data/scripts/medpy_binary_resampling.py
MedPy2-0.0.2.data/scripts/medpy_convert.py
MedPy2-0.0.2.data/scripts/medpy_create_empty_volume_by_example.py
MedPy2-0.0.2.data/scripts/medpy_dicom_slices_to_volume.py
MedPy2-0.0.2.data/scripts/medpy_dicom_to_4D.py
MedPy2-0.0.2.data/scripts/medpy_diff.py
MedPy2-0.0.2.data/scripts/medpy_extract_contour.py
MedPy2-0.0.2.data/scripts/medpy_extract_min_max.py
MedPy2-0.0.2.data/scripts/medpy_extract_sub_volume.py
MedPy2-0.0.2.data/scripts/medpy_extract_sub_volume_auto.py
MedPy2-0.0.2.data/scripts/medpy_extract_sub_volume_by_example.py
MedPy2-0.0.2.data/scripts/medpy_fit_into_shape.py
MedPy2-0.0.2.data/scripts/medpy_gradient.py
MedPy2-0.0.2.data/scripts/medpy_graphcut_label.py
MedPy2-0.0.2.data/scripts/medpy_graphcut_label_bgreduced.py
MedPy2-0.0.2.data/scripts/medpy_graphcut_label_w_regional.py
MedPy2-0.0.2.data/scripts/medpy_graphcut_label_wsplit.py
MedPy2-0.0.2.data/scripts/medpy_graphcut_voxel.py
MedPy2-0.0.2.data/scripts/medpy_grid.py
MedPy2-0.0.2.data/scripts/medpy_info.py
MedPy2-0.0.2.data/scripts/medpy_intensity_range_standardization.py
MedPy2-0.0.2.data/scripts/medpy_intersection.py
MedPy2-0.0.2.data/scripts/medpy_join_masks.py
MedPy2-0.0.2.data/scripts/medpy_join_xd_to_xplus1d.py
MedPy2-0.0.2.data/scripts/medpy_label_count.py
MedPy2-0.0.2.data/scripts/medpy_label_fit_to_mask.py
MedPy2-0.0.2.data/scripts/medpy_label_superimposition.py
MedPy2-0.0.2.data/scripts/medpy_merge.py
MedPy2-0.0.2.data/scripts/medpy_morphology.py
MedPy2-0.0.2.data/scripts/medpy_resample.py
MedPy2-0.0.2.data/scripts/medpy_reslice_3d_to_4d.py
MedPy2-0.0.2.data/scripts/medpy_set_pixel_spacing.py
MedPy2-0.0.2.data/scripts/medpy_shrink_image.py
MedPy2-0.0.2.data/scripts/medpy_split_xd_to_xminus1d.py
MedPy2-0.0.2.data/scripts/medpy_stack_sub_volumes.py
MedPy2-0.0.2.data/scripts/medpy_swap_dimensions.py
MedPy2-0.0.2.dist-info/LICENSE.txt
MedPy2-0.0.2.dist-info/METADATA
MedPy2-0.0.2.dist-info/WHEEL
MedPy2-0.0.2.dist-info/top_level.txt
MedPy2-0.0.2.dist-info/RECORD
