Metadata-Version: 2.1
Name: MedPy2
Version: 0.0.2
Summary: Medical image processing in Python
License: LICENSE.txt
Keywords: medical image processing dicom itk insight tool kit MRI CT US graph cut max-flow min-cut
Classifier: Development Status :: 5 - Production/Stable
Classifier: Environment :: Console
Classifier: Environment :: Other Environment
Classifier: Intended Audience :: End Users/Desktop
Classifier: Intended Audience :: Developers
Classifier: Intended Audience :: Healthcare Industry
Classifier: Intended Audience :: Science/Research
Classifier: License :: OSI Approved :: GNU General Public License (GPL)
Classifier: Operating System :: MacOS :: MacOS X
Classifier: Operating System :: Microsoft :: Windows
Classifier: Operating System :: POSIX
Classifier: Operating System :: Unix
Classifier: Programming Language :: Python :: 3.5
Classifier: Programming Language :: Python :: 3.6
Classifier: Programming Language :: C++
Classifier: Topic :: Scientific/Engineering :: Medical Science Apps.
Classifier: Topic :: Scientific/Engineering :: Image Recognition
License-File: LICENSE.txt
Requires-Dist: scipy >=1.1.0
Requires-Dist: numpy >=1.11.0
Requires-Dist: SimpleITK >=1.1.0
